lariat_client/__init__.py
lariat_client/lariat_client.py
lariat_python_sdk-0.1.6.dist-info/LICENSE
lariat_python_sdk-0.1.6.dist-info/METADATA
lariat_python_sdk-0.1.6.dist-info/WHEEL
lariat_python_sdk-0.1.6.dist-info/top_level.txt
lariat_python_sdk-0.1.6.dist-info/RECORD
