Metadata-Version: 2.1
Name: lariat_python_sdk
Version: 0.1.6
Summary: A Python module to interact with Lariat API to access data quality metrics and diagnostics
Author-email: Lariat Data Team <info@lariatdata.com>
License: BSD-3-Clause
Project-URL: homepage, https://www.lariatdata.com
Project-URL: documentation, https://lariat-python-sdk.readthedocs.io/en/latest/
Project-URL: repository, https://github.com/lariat-data/lariat-python-sdk
Classifier: Development Status :: 3 - Alpha
Classifier: Intended Audience :: Developers
Classifier: License :: OSI Approved :: BSD License
Classifier: Operating System :: OS Independent
Classifier: Programming Language :: Python
Classifier: Programming Language :: Python :: 3
Classifier: Programming Language :: Python :: 3.6
Classifier: Programming Language :: Python :: 3.7
Classifier: Programming Language :: Python :: 3.8
Classifier: Programming Language :: Python :: 3.9
License-File: LICENSE
Requires-Dist: python-dotenv
Requires-Dist: requests
Requires-Dist: pandas
Requires-Dist: flatten-json
